traffy/README.md
traffy/__init__.py
traffy/simulation.py
traffy/version
traffy-0.0.1.dist-info/LICENSE
traffy-0.0.1.dist-info/METADATA
traffy-0.0.1.dist-info/WHEEL
traffy-0.0.1.dist-info/top_level.txt
traffy-0.0.1.dist-info/RECORD
