Metadata-Version: 2.1
Name: traffy
Version: 0.0.1
Summary: A package traffy.
Home-page: https://github.com/rahulbhadani/traffy
Author: Rahul Bhadani
Author-email: rahulbhadani@email.arizona.edu
License: UNKNOWN
Keywords: python
Platform: UNKNOWN
Classifier: Programming Language :: Python :: 3
Classifier: Framework :: AsyncIO
Classifier: Topic :: Communications
Classifier: Topic :: Scientific/Engineering :: Visualization
Classifier: License :: OSI Approved :: MIT License
Requires-Dist: setuptools
